doit_report.py
doit_report-0.1.dist-info/DESCRIPTION.rst
doit_report-0.1.dist-info/METADATA
doit_report-0.1.dist-info/RECORD
doit_report-0.1.dist-info/WHEEL
doit_report-0.1.dist-info/entry_points.txt
doit_report-0.1.dist-info/metadata.json
doit_report-0.1.dist-info/top_level.txt
