Metadata-Version: 2.0
Name: doit-report
Version: 0.1
Summary: Show ASCII or HTML report for doit task execution status
Home-page: http://github.com/saimn/doit-report
Author: Simon Conseil
Author-email: contact@saimon.org
License: MIT
Keywords: doit
Platform: any
Requires-Python: >=3.5
Requires-Dist: doit
Requires-Dist: astropy
